{
  "title": {
    "name": "Title",
    "type": "Symbol",
    "localized": false,
    "required": true,
    "validations": [
      {
        "unique": true
      }
    ],
    "disabled": false,
    "omitted": false
  },
  "slug": {
    "name": "Slug",
    "type": "Symbol",
    "localized": false,
    "required": false,
    "validations": [
      {
        "unique": true
      }
    ],
    "disabled": false,
    "omitted": false
  },
  "hero": {
    "name": "Hero",
    "type": "Link",
    "localized": false,
    "required": false,
    "validations": [
      {
        "linkContentType": ["hero"]
      }
    ],
    "disabled": false,
    "omitted": false,
    "linkType": "Entry"
  },
  "showSignUpBanner": {
    "name": "Show Sign Up Banner",
    "type": "Boolean",
    "localized": false,
    "required": false,
    "validations": [],
    "disabled": false,
    "omitted": false
  }
}
